<annotation>
	<folder>train_wavelet</folder>
	<filename>wavelet_hor_6406_3_2_4006_4007.jpg</filename>
	<path>/home/dennis/Documents/object_detection_coreplug/core_plug_data/images/train_wavelet/wavelet_hor_6406_3_2_4006_4007.jpg</path>
	<source>
		<database>Unknown</database>
	</source>
	<size>
		<width>215</width>
		<height>1929</height>
		<depth>1</depth>
	</size>
	<segmented>0</segmented>
	<object>
		<name>hplug</name>
		<pose>Unspecified</pose>
		<truncated>0</truncated>
		<difficult>0</difficult>
		<bndbox>
			<xmin>130</xmin>
			<ymin>249</ymin>
			<xmax>208</xmax>
			<ymax>321</ymax>
		</bndbox>
	</object>
	<object>
		<name>hplug</name>
		<pose>Unspecified</pose>
		<truncated>0</truncated>
		<difficult>0</difficult>
		<bndbox>
			<xmin>120</xmin>
			<ymin>1423</ymin>
			<xmax>200</xmax>
			<ymax>1501</ymax>
		</bndbox>
	</object>
	<object>
		<name>hplug</name>
		<pose>Unspecified</pose>
		<truncated>0</truncated>
		<difficult>0</difficult>
		<bndbox>
			<xmin>118</xmin>
			<ymin>959</ymin>
			<xmax>204</xmax>
			<ymax>1033</ymax>
		</bndbox>
	</object>
	<object>
		<name>vplug</name>
		<pose>Unspecified</pose>
		<truncated>0</truncated>
		<difficult>0</difficult>
		<bndbox>
			<xmin>20</xmin>
			<ymin>1411</ymin>
			<xmax>88</xmax>
			<ymax>1547</ymax>
		</bndbox>
	</object>
	<object>
		<name>vplug</name>
		<pose>Unspecified</pose>
		<truncated>1</truncated>
		<difficult>0</difficult>
		<bndbox>
			<xmin>28</xmin>
			<ymin>1829</ymin>
			<xmax>86</xmax>
			<ymax>1929</ymax>
		</bndbox>
	</object>
	<object>
		<name>vplug</name>
		<pose>Unspecified</pose>
		<truncated>0</truncated>
		<difficult>0</difficult>
		<bndbox>
			<xmin>40</xmin>
			<ymin>209</ymin>
			<xmax>120</xmax>
			<ymax>389</ymax>
		</bndbox>
	</object>
	<object>
		<name>hplug</name>
		<pose>Unspecified</pose>
		<truncated>0</truncated>
		<difficult>0</difficult>
		<bndbox>
			<xmin>102</xmin>
			<ymin>1817</ymin>
			<xmax>184</xmax>
			<ymax>1891</ymax>
		</bndbox>
	</object>
	<object>
		<name>scal</name>
		<pose>Unspecified</pose>
		<truncated>0</truncated>
		<difficult>0</difficult>
		<bndbox>
			<xmin>62</xmin>
			<ymin>415</ymin>
			<xmax>164</xmax>
			<ymax>515</ymax>
		</bndbox>
	</object>
	<object>
		<name>scal</name>
		<pose>Unspecified</pose>
		<truncated>0</truncated>
		<difficult>0</difficult>
		<bndbox>
			<xmin>62</xmin>
			<ymin>515</ymin>
			<xmax>166</xmax>
			<ymax>611</ymax>
		</bndbox>
	</object>
</annotation>